logisticRegression/__init__.py
logisticRegression/main.py
logisticregression-2025.0.0.dist-info/METADATA
logisticregression-2025.0.0.dist-info/WHEEL
logisticregression-2025.0.0.dist-info/top_level.txt
logisticregression-2025.0.0.dist-info/RECORD
