Metadata-Version: 2.4
Name: logisticRegression
Version: 2025.0.0
Requires-Python: >=3.9
Requires-Dist: numpy
Requires-Dist: pandas
